universal_tester/__init__.py
universal_tester/cli.py
universal_tester/core.py
universal_tester/detectors/__init__.py
universal_tester/detectors/enhanced_import_detector.py
universal_tester/detectors/kotlin_import_detector.py
universal_tester/llm/__init__.py
universal_tester/llm/factory.py
universal_tester/llm/health_check.py
universal_tester/llm/java_validator.py
universal_tester/prompts/__init__.py
universal_tester/prompts/kotlin_test_generation_prompts.py
universal_tester/prompts/prompt_builder.py
universal_tester/prompts/system_prompts.py
universal_tester/prompts/test_generation_prompts.py
universal_tester/prompts/ui_messages.py
universal_tester/ui/__init__.py
universal_tester/ui/chainlit.md
universal_tester/ui/chainlit.toml
universal_tester/ui/chainlit_ui.py
universal_tester/ui/main.py
universal_tester-1.1.1.dist-info/licenses/LICENSE
universal_tester-1.1.1.dist-info/METADATA
universal_tester-1.1.1.dist-info/WHEEL
universal_tester-1.1.1.dist-info/entry_points.txt
universal_tester-1.1.1.dist-info/top_level.txt
universal_tester-1.1.1.dist-info/RECORD
