Metadata-Version: 2.4
Name: universal-tester
Version: 1.1.1
Summary: AI-powered automatic test case generation for Java and Kotlin projects with Web UI and CLI
Author-email: Senthil Kumar Thanapal <senthilthepro@hotmail.com>
License: Apache-2.0
Project-URL: Homepage, https://pypi.org/project/universal-tester/
Project-URL: Documentation, https://pypi.org/project/universal-tester/
Project-URL: Repository, https://pypi.org/project/universal-tester/
Keywords: testing,test-generation,junit,java,kotlin,ai,llm,automation,spring-boot,mockito
Classifier: Development Status :: 4 - Beta
Classifier: Intended Audience :: Developers
Classifier: Topic :: Software Development :: Testing
Classifier: Topic :: Software Development :: Quality Assurance
Classifier: License :: OSI Approved :: Apache Software License
Classifier: Programming Language :: Python :: 3
Classifier: Programming Language :: Python :: 3.8
Classifier: Programming Language :: Python :: 3.9
Classifier: Programming Language :: Python :: 3.10
Classifier: Programming Language :: Python :: 3.11
Classifier: Programming Language :: Python :: 3.12
Classifier: Programming Language :: Java
Classifier: Programming Language :: Other
Classifier: Framework :: AsyncIO
Requires-Python: >=3.8
License-File: LICENSE
Requires-Dist: langchain<0.3.0,>=0.1.0
Requires-Dist: langchain-openai<0.3.0,>=0.1.0
Requires-Dist: langchain-community<0.3.0,>=0.0.30
Requires-Dist: python-dotenv>=1.0.0
Requires-Dist: requests>=2.31.0
Requires-Dist: typing-extensions>=4.0.0
Requires-Dist: pyyaml>=6.0
Requires-Dist: chainlit>=1.1.0
Provides-Extra: google
Requires-Dist: langchain-google-genai>=0.0.3; extra == "google"
Requires-Dist: google-generativeai>=0.3.0; extra == "google"
Provides-Extra: dev
Requires-Dist: pytest>=7.0.0; extra == "dev"
Requires-Dist: pytest-asyncio>=0.21.0; extra == "dev"
Requires-Dist: black>=23.0.0; extra == "dev"
Requires-Dist: flake8>=6.0.0; extra == "dev"
Requires-Dist: mypy>=1.0.0; extra == "dev"
Requires-Dist: build>=0.10.0; extra == "dev"
Requires-Dist: twine>=4.0.0; extra == "dev"
Provides-Extra: all
Requires-Dist: universal-tester[dev,google]; extra == "all"
Dynamic: license-file
